satio/__init__.py
satio/_version.py
satio/collections.py
satio/features.py
satio/geoloader.py
satio/grid.py
satio/rsindices.py
satio/seasons.py
satio/timeseries.py
satio/layers/__init__.py
satio/layers/ecoregions2017_simplified.geojson
satio/layers/ne_countries_simple.geojson
satio/layers/ne_landsea_simple.geojson
satio/layers/s2grid_all_bounds.geojson
satio/layers/s2grid_bounds.geojson
satio/layers/sentinel2_jp2_windows.json
satio/utils/__init__.py
satio/utils/aws.py
satio/utils/buildvrt.py
satio/utils/cog.py
satio/utils/composite.py
satio/utils/errors.py
satio/utils/geotiff.py
satio/utils/googlemaps.py
satio/utils/imviewer.py
satio/utils/interpolation.py
satio/utils/logs.py
satio/utils/nanpercentile.py
satio/utils/nonzeropercentile.py
satio/utils/resample.py
satio/utils/retry.py
satio/utils/speckle.py
satio/utils/texture.py
satio/utils/visualizer.py
satio-1.2.3.dist-info/METADATA
satio-1.2.3.dist-info/WHEEL
satio-1.2.3.dist-info/RECORD
