Metadata-Version: 2.4
Name: satio
Version: 1.2.3
Summary: Sentinel-2 processing utilities
Author: VITO RS LCF team
Requires-Python: <3.12,>=3.10
Requires-Dist: boto3>=1.11.9
Requires-Dist: geopandas>=0.7.0
Requires-Dist: h5netcdf
Requires-Dist: importlib-resources
Requires-Dist: joblib>=0.17.0
Requires-Dist: loguru>=0.5.3
Requires-Dist: matplotlib>=3.5.3
Requires-Dist: numba>=0.48.0
Requires-Dist: openeo>=0.4.8
Requires-Dist: pandas
Requires-Dist: psutil>=5.7.3
Requires-Dist: rasterio>=1.1.1
Requires-Dist: rio-cogeo>=3.4.1
Requires-Dist: scikit-image
Requires-Dist: scikit-learn>=0.22.1
Requires-Dist: shapely
Requires-Dist: tqdm
Requires-Dist: xarray>=0.12.3
